drfbp/__init__.py
drfbp/__main__.py
drfbp/permissions.py
drfbp/serializers.py
drfbp/urls.py
drfbp/views.py
drfbp-2025.6.19.dist-info/licenses/LICENSE.txt
drfbp-2025.6.19.dist-info/METADATA
drfbp-2025.6.19.dist-info/WHEEL
drfbp-2025.6.19.dist-info/entry_points.txt
drfbp-2025.6.19.dist-info/top_level.txt
drfbp-2025.6.19.dist-info/RECORD
