Metadata-Version: 2.4
Name: drfbp
Version: 2025.6.19
Summary: Django REST Framework Boilerplate Generator
Author-email: Dado <gerardoaballesterjr@gmail.com>
License: MIT
Keywords: drf,django,rest framework,boilerplate,generator
Classifier: Programming Language :: Python :: 3
Classifier: License :: OSI Approved :: MIT License
Classifier: Operating System :: OS Independent
Requires-Python: >=3.8
License-File: LICENSE.txt
Dynamic: license-file
